e57-0.2.1a1.dist-info/METADATA
e57-0.2.1a1.dist-info/WHEEL
e57-0.2.1a1.dist-info/licenses/LICENSE
e57/__init__.py
e57/e57.cp313-win32.pyd
e57-0.2.1a1.dist-info/RECORD
